fyle/__init__.py
fyle/platform/__init__.py
fyle/platform/exceptions.py
fyle/platform/platform.py
fyle/platform/apis/__init__.py
fyle/platform/apis/v1/__init__.py
fyle/platform/apis/v1/version.py
fyle/platform/apis/v1/accountant/__init__.py
fyle/platform/apis/v1/accountant/orgs.py
fyle/platform/apis/v1/admin/__init__.py
fyle/platform/apis/v1/admin/accounting_exports.py
fyle/platform/apis/v1/admin/advance_requests.py
fyle/platform/apis/v1/admin/categories.py
fyle/platform/apis/v1/admin/corporate_card_transactions.py
fyle/platform/apis/v1/admin/corporate_cards.py
fyle/platform/apis/v1/admin/cost_centers.py
fyle/platform/apis/v1/admin/departments.py
fyle/platform/apis/v1/admin/dependent_expense_field_values.py
fyle/platform/apis/v1/admin/employees.py
fyle/platform/apis/v1/admin/expense_fields.py
fyle/platform/apis/v1/admin/expenses.py
fyle/platform/apis/v1/admin/files.py
fyle/platform/apis/v1/admin/org_settings.py
fyle/platform/apis/v1/admin/projects.py
fyle/platform/apis/v1/admin/reimbursements.py
fyle/platform/apis/v1/admin/reports.py
fyle/platform/apis/v1/admin/scheduled_callbacks.py
fyle/platform/apis/v1/admin/subscriptions.py
fyle/platform/apis/v1/admin/tax_groups.py
fyle/platform/apis/v1/approver/__init__.py
fyle/platform/apis/v1/approver/categories.py
fyle/platform/apis/v1/approver/expenses.py
fyle/platform/apis/v1/approver/projects.py
fyle/platform/apis/v1/approver/reports.py
fyle/platform/apis/v1/common/__init__.py
fyle/platform/apis/v1/common/currencies.py
fyle/platform/apis/v1/common/expense_extract.py
fyle/platform/apis/v1/common/places.py
fyle/platform/apis/v1/spender/__init__.py
fyle/platform/apis/v1/spender/accounts.py
fyle/platform/apis/v1/spender/categories.py
fyle/platform/apis/v1/spender/corporate_cards.py
fyle/platform/apis/v1/spender/cost_centers.py
fyle/platform/apis/v1/spender/employees.py
fyle/platform/apis/v1/spender/expense_fields.py
fyle/platform/apis/v1/spender/expenses.py
fyle/platform/apis/v1/spender/files.py
fyle-1.1.2.dist-info/licenses/LICENSE
fyle-1.1.2.dist-info/METADATA
fyle-1.1.2.dist-info/WHEEL
fyle-1.1.2.dist-info/top_level.txt
fyle-1.1.2.dist-info/RECORD
