Metadata-Version: 2.4
Name: fyle
Version: 1.1.2
Summary: Python SDK for accessing Fyle Platform APIs
Home-page: https://github.com/fylein/fyle-platform-sdk-py
Author: Siva Narayanan
Author-email: siva@fyle.in
License: MIT
Keywords: fyle,api,python,sdk
Classifier: Topic :: Internet :: WWW/HTTP
Classifier: Intended Audience :: Developers
Classifier: Programming Language :: Python :: 3
Classifier: License :: OSI Approved :: MIT License
Classifier: Operating System :: OS Independent
License-File: LICENSE
Requires-Dist: enum34>=1.1.10
Requires-Dist: requests>=2.32.3
Dynamic: author
Dynamic: author-email
Dynamic: classifier
Dynamic: description
Dynamic: description-content-type
Dynamic: home-page
Dynamic: keywords
Dynamic: license
Dynamic: license-file
Dynamic: requires-dist
Dynamic: summary
